ybckit/__init__.py
ybckit/config.py
ybckit/gui.py
ybckit/log.py
ybckit/media.py
ybckit/mpl.py
ybckit/protocol.py
ybckit/runner.py
ybckit-0.0.55.dist-info/METADATA
ybckit-0.0.55.dist-info/RECORD
ybckit-0.0.55.dist-info/WHEEL
ybckit-0.0.55.dist-info/entry_points.txt
ybckit-0.0.55.dist-info/top_level.txt
