Metadata-Version: 2.1
Name: ybckit
Version: 0.0.55
Summary: Python library kit for education with yuanfudao.
Home-page: https://github.com/yuantiku/ybckit
Author: Yuchen <pw> Zhang
Author-email: zhangyc@fenbi.com
License: UNKNOWN
Project-URL: Source, https://github.com/yuantiku/ybckit/
Project-URL: Bug Reports, https://github.com/yuantiku/ybckit/issues
Keywords: yuanfudao gui media kit
Platform: UNKNOWN
Provides-Extra: test
Provides-Extra: dev
Requires-Dist: easygui
Requires-Dist: pathlib
Requires-Dist: matplotlib
Requires-Dist: mpld3
Requires-Dist: openpyxl
Requires-Dist: jinja2
Requires-Dist: ybc-box
Requires-Dist: pyaudio
Requires-Dist: wave
Requires-Dist: ybc-speech
Requires-Dist: ybc-face
Provides-Extra: dev
Requires-Dist: check-manifest; extra == 'dev'
Provides-Extra: test
Requires-Dist: coverage; extra == 'test'
Requires-Dist: numpy; extra == 'test'
